stopPhishing/__init__.py
stopPhishing/functions/amount.py
stopPhishing/functions/check.py
stopPhishing/functions/list.py
stopPhishing-0.0.2.dist-info/LICENSE
stopPhishing-0.0.2.dist-info/METADATA
stopPhishing-0.0.2.dist-info/WHEEL
stopPhishing-0.0.2.dist-info/top_level.txt
stopPhishing-0.0.2.dist-info/RECORD
